lightweight_s3/__init__.py
lightweight_s3/__init__.pyi
lightweight_s3/py.typed
lightweight_s3/core/__init__.py
lightweight_s3/core/__init__.pyi
lightweight_s3/core/s3_client.py
lightweight_s3/core/s3_client.pyi
lightweight_s3/core/storage_connection_parameters.py
lightweight_s3/core/storage_connection_parameters.pyi
lightweight_s3-0.0.5.dist-info/licenses/LICENSE
lightweight_s3-0.0.5.dist-info/METADATA
lightweight_s3-0.0.5.dist-info/WHEEL
lightweight_s3-0.0.5.dist-info/top_level.txt
lightweight_s3-0.0.5.dist-info/RECORD
