Metadata-Version: 2.4
Name: lightweight-s3
Version: 0.0.5
Summary: Lightweight S3 client with backblaze support
Home-page: https://www.youtube.com/watch?v=dQw4w9WgXcQ
Author: Daniel Lasota
Author-email: grossmann.root@gmail.com
Project-URL: Source, https://github.com/DanielLasota/lightweight-s3
Keywords: s3 backblaze boto3 client
Requires-Python: >=3.11
License-File: LICENSE
Requires-Dist: requests
Dynamic: author
Dynamic: author-email
Dynamic: description
Dynamic: description-content-type
Dynamic: home-page
Dynamic: keywords
Dynamic: license-file
Dynamic: project-url
Dynamic: requires-dist
Dynamic: requires-python
Dynamic: summary
